dockercontext/__init__.py
dockercontext/container.py
tests/__init__.py
tests/test_container.py
dockercontext-0.1.dist-info/LICENSE
dockercontext-0.1.dist-info/METADATA
dockercontext-0.1.dist-info/WHEEL
dockercontext-0.1.dist-info/top_level.txt
dockercontext-0.1.dist-info/RECORD
