Metadata-Version: 2.1
Name: dockercontext
Version: 0.1
Summary: Run Docker containers within Python context manager
Home-page: https://github.com/peknur/dockercontext
Author: Pekka Nurmi
Author-email: peknur@gmail.com
License: UNKNOWN
Platform: UNKNOWN
Classifier: Programming Language :: Python :: 3
Classifier: License :: OSI Approved :: MIT License
Requires-Python: >=3.8
Requires-Dist: docker
